Metadata-Version: 1.1
Name: nats-client
Version: 0.8.2
Summary: NATS client for Python 2
Home-page: https://github.com/nats-io/python-nats
Author: Waldemar Quevedo
Author-email: wally@synadia.com
License: Apache 2.0 License
Platform: UNKNOWN
Classifier: Intended Audience :: Developers
Classifier: Programming Language :: Python
